sqlitefid/__init__.py
sqlitefid/sqlitefid.py
sqlitefid/libs/CSVHandlerClass.py
sqlitefid/libs/DROIDLoaderClass.py
sqlitefid/libs/FidoLoaderClass.py
sqlitefid/libs/GenerateBaselineDBClass.py
sqlitefid/libs/IdentifyExportClass.py
sqlitefid/libs/PyDateHandler.py
sqlitefid/libs/SFHandlerClass.py
sqlitefid/libs/SFLoaderClass.py
sqlitefid/libs/ToolMappingClass.py
sqlitefid/libs/Version.py
sqlitefid/libs/__init__.py
sqlitefid/libs/unicodecsv.py
sqlitefid-3.0.0rc2.dist-info/LICENSE
sqlitefid-3.0.0rc2.dist-info/METADATA
sqlitefid-3.0.0rc2.dist-info/WHEEL
sqlitefid-3.0.0rc2.dist-info/entry_points.txt
sqlitefid-3.0.0rc2.dist-info/top_level.txt
sqlitefid-3.0.0rc2.dist-info/RECORD
